streamlit_url_fragment/__init__.py
streamlit_url_fragment/build/asset-manifest.json
streamlit_url_fragment/build/index.html
streamlit_url_fragment/build/static/js/2.16f151e3.chunk.js
streamlit_url_fragment/build/static/js/2.16f151e3.chunk.js.LICENSE.txt
streamlit_url_fragment/build/static/js/2.16f151e3.chunk.js.map
streamlit_url_fragment/build/static/js/main.171be1f5.chunk.js
streamlit_url_fragment/build/static/js/main.171be1f5.chunk.js.map
streamlit_url_fragment/build/static/js/runtime-main.6dd7e1ed.js
streamlit_url_fragment/build/static/js/runtime-main.6dd7e1ed.js.map
streamlit_url_fragment/package-lock.json
streamlit_url_fragment/package.json
streamlit_url_fragment/public/index.html
streamlit_url_fragment/src/index.ts
streamlit_url_fragment/src/react-app-env.d.ts
streamlit_url_fragment/tsconfig.json
streamlit_url_fragment-0.2.1.dist-info/WHEEL
streamlit_url_fragment-0.2.1.dist-info/METADATA
streamlit_url_fragment-0.2.1.dist-info/RECORD
