Metadata-Version: 2.1
Name: streamlit-url-fragment
Version: 0.2.1
Summary: Get the URL fragment (part after #) from Streamlit
License: Apache-2.0
Author: Tomasz Kontusz
Author-email: tomasz.kontusz@gmail.com
Requires-Python: >=3.8,<4.0
Classifier: License :: OSI Approved :: Apache Software License
Classifier: Programming Language :: Python :: 3
Classifier: Programming Language :: Python :: 3.10
Classifier: Programming Language :: Python :: 3.8
Classifier: Programming Language :: Python :: 3.9
Requires-Dist: importlib-resources (>=5.4.0,<6.0.0)
Requires-Dist: streamlit (>0.63)
